network.py
network_wrapper-0.4.dist-info/METADATA
network_wrapper-0.4.dist-info/WHEEL
network_wrapper-0.4.dist-info/copyright
network_wrapper-0.4.dist-info/top_level.txt
network_wrapper-0.4.dist-info/RECORD
