Metadata-Version: 2.1
Name: network-wrapper
Version: 0.4
Summary: module for easy networking
Home-page: https://github.com/wijnen/python-network
Author: Bas Wijnen
Author-email: wijnen@debian.org
License: AGPL3+
Project-URL: Bug Tracker, https://github.com/wijnen/python-network/issues
Classifier: Programming Language :: Python :: 3
Classifier: License :: OSI Approved :: GNU Affero General Public License v3 or later (AGPLv3+)
Classifier: Intended Audience :: Developers
Classifier: Development Status :: 4 - Beta
Classifier: Operating System :: OS Independent
Classifier: Topic :: System :: Networking
Requires-Python: >=3
License-File: debian/copyright
Requires-Dist: fhs-paths
